{
	"grid": [
        {
            "category": "Job Security",
            "question": "Do you feel your job is secure?",
            "priority": "High",
            "updated": "2016-02-17",
            "status": "<input id=toggle1 class='toggle__input toggle__input--small' type=checkbox checked><label for=toggle1 class='toggle__label toggle__label--small'></label>"
        },
        {
            "category": "Job Security",
            "question": "I have a sense of security in my job",
            "priority": "Low",
            "updated": "2016-02-17",
            "status": "<input id=toggle2 class='toggle__input toggle__input--small' type=checkbox checked><label for=toggle2 class='toggle__label toggle__label--small'></label>"
        },
        {
            "category": "Job Security",
            "question": "I sometimes fear losing my job",
            "priority": "Low",
            "updated": "2016-02-17",
            "status": "<input id=toggle3 class='toggle__input toggle__input--small' type=checkbox checked><label for=toggle3 class='toggle__label toggle__label--small'></label>"
        },
        {
            "category": "Job Satisfaction",
            "question": "I enjoy working at GE",
            "priority": "High",
            "updated": "2016-02-17",
            "status": "<input id=toggle4 class='toggle__input toggle__input--small' type=checkbox checked><label for=toggle4 class='toggle__label toggle__label--small'></label>"
        },
        {
            "category": "Job Satisfaction",
            "question": "I am proud to tell others I work for GE",
            "priority": "Low",
            "updated": "2016-02-17",
            "status": "<input id=toggle5 class='toggle__input toggle__input--small' type=checkbox checked><label for=toggle5 class='toggle__label toggle__label--small'></label>"
        },
        {
            "category": "Job Satisfaction",
            "question": "I am made to feel that I am an important part of GE",
            "priority": "Low",
            "updated": "2016-02-17",
            "status": "<input id=toggle6 class='toggle__input toggle__input--small' type=checkbox checked><label for=toggle6 class='toggle__label toggle__label--small'></label>"
        },
        {
            "category": "Job Satisfaction",
            "question": "Personal Satisfaction",
            "priority": "Low",
            "updated": "2016-02-17",
            "status": "<input id=toggle7 class='toggle__input toggle__input--small' type=checkbox><label for=toggle7 class='toggle__label toggle__label--small'></label>"
        },
        {
            "category": "Job Satisfaction",
            "question": "I receive personal satisfaction from doing a good job",
            "priority": "Low",
            "updated": "2016-02-17",
            "status": "<input id=toggle8 class='toggle__input toggle__input--small' type=checkbox><label for=toggle8 class='toggle__label toggle__label--small'></label>"
        },
        {
            "category": "Job Satisfaction",
            "question": "My job is rewarding",
            "priority": "Low",
            "updated": "2016-02-17",
            "status": "<input id=toggle9 class='toggle__input toggle__input--small' type=checkbox><label for=toggle9 class='toggle__label toggle__label--small'></label>"
        },
        {
            "category": "Job Satisfaction",
            "question": "I get a sense of personal accomplishment from my work",
            "priority": "Low",
            "updated": "2016-02-17",
            "status": "<input id=toggle10 class='toggle__input toggle__input--small' type=checkbox><label for=toggle10 class='toggle__label toggle__label--small'></label>"
        },
        {
            "category": "Job Satisfaction",
            "question": "I feel appreciated at work",
            "priority": "Low",
            "updated": "2016-02-15",
            "status": "<input id=toggle11 class='toggle__input toggle__input--small' type=checkbox><label for=toggle11 class='toggle__label toggle__label--small'></label>"
        }
	]
}